formgram/__init__.py
formgram/classes/__init__.py
formgram/classes/finite_automaton.py
formgram/classes/grammar.py
formgram/classes/pushdown_automaton.py
formgram/classes/turing_machine.py
formgram/formgram_classes/__init__.py
formgram/formgram_classes/grammar_base.py
formgram/formgram_machines/__init__.py
formgram/formgram_machines/finite_automata/__init__.py
formgram/formgram_machines/finite_automata/classifiers.py
formgram/formgram_machines/finite_automata/grammar_interface.py
formgram/formgram_machines/finite_automata/simulation_functions.py
formgram/formgram_machines/finite_automata/transformations.py
formgram/formgram_machines/finite_automata/utilities.py
formgram/formgram_machines/helper_functions/__init__.py
formgram/formgram_machines/helper_functions/nested_dictionaries.py
formgram/formgram_machines/push_down_automata/__init__.py
formgram/formgram_machines/push_down_automata/grammar_interface.py
formgram/formgram_machines/push_down_automata/simulation_functions.py
formgram/formgram_machines/push_down_automata/utilities.py
formgram/formgram_machines/turing_machines/__init__.py
formgram/formgram_machines/turing_machines/grammar_interface.py
formgram/formgram_machines/turing_machines/simulation_functions.py
formgram/formgram_machines/turing_machines/subroutines.py
formgram/formgram_machines/turing_machines/transformations.py
formgram/formgram_procedures/__init__.py
formgram/formgram_procedures/classifiers/__init__.py
formgram/formgram_procedures/classifiers/chomsky_classifiers.py
formgram/formgram_procedures/classifiers/form_classifiers.py
formgram/formgram_procedures/helper_functions/__init__.py
formgram/formgram_procedures/helper_functions/decorators.py
formgram/formgram_procedures/helper_functions/input_validator.py
formgram/formgram_procedures/helper_functions/production_grouping.py
formgram/formgram_procedures/helper_functions/sequence_functions.py
formgram/formgram_procedures/helper_functions/set_functions.py
formgram-0.0.6.dist-info/LICENSE
formgram-0.0.6.dist-info/METADATA
formgram-0.0.6.dist-info/WHEEL
formgram-0.0.6.dist-info/top_level.txt
formgram-0.0.6.dist-info/RECORD
