Metadata-Version: 2.1
Name: formgram
Version: 0.0.6
Summary: formal grammar teaching toolkit
Home-page: https://theodor.moeser.pages.gwdg.de/formgram2022
Author: Theodor Möser
Author-email: th.moeser@gmx.de
License: UNKNOWN
Platform: UNKNOWN
Classifier: Development Status :: 2 - Pre-Alpha
Classifier: Programming Language :: Python :: 3
Classifier: Programming Language :: Python :: 3.8
Classifier: License :: OSI Approved :: European Union Public Licence 1.2 (EUPL 1.2)
Classifier: Operating System :: OS Independent
License-File: LICENSE
Requires-Dist: ply
Requires-Dist: graphviz
